Metadata-Version: 2.1
Name: keymapper
Version: 1.0.0
Summary: A dynamic dictionary iteration tool that allows you to get and set keys and values with a single key declaration
Home-page: https://gitlab.com/rburns629/KeyMapper
Author: Robert Burns
Author-email: rburns629@gmail.com
License: UNKNOWN
Project-URL: Bug Reports, https://gitlab.com/rburns629/KeyMapper/issues
Project-URL: Source, https://gitlab.com/rburns629/KeyMapper
Keywords: dict dot delimeter key map dynamic
Platform: UNKNOWN
Classifier: Development Status :: 5 - Production/Stable
Classifier: Intended Audience :: Developers
Classifier: Topic :: Software Development :: Build Tools
Classifier: License :: OSI Approved :: MIT License
Classifier: Programming Language :: Python :: 3
Classifier: Programming Language :: Python :: 3.4
Classifier: Programming Language :: Python :: 3.5
Classifier: Programming Language :: Python :: 3.6
